cimod/CMakeLists.txt
cimod/__init__.py
cimod/_version.py
cimod/cxxcimod.cpython-39-x86_64-linux-gnu.so
cimod/main.cpp
cimod/main.hpp
cimod/vartype.py
cimod/model/__init__.py
cimod/model/binary_polynomial_model.py
cimod/model/binary_quadratic_model.py
cimod/model/legacy/__init__.py
cimod/model/legacy/binary_quadratic_model.py
cimod/utils/__init__.py
cimod/utils/decolator.py
cimod/utils/response.py
jij_cimod.libs/libimf-a036d58f.so
jij_cimod.libs/libintlc-360a6e7a.so.5
jij_cimod.libs/libiomp5-c8421531.so
jij_cimod.libs/libirng-689a856c.so
jij_cimod.libs/libsvml-8743a5d3.so
jij_cimod-1.7.3.dist-info/METADATA
jij_cimod-1.7.3.dist-info/WHEEL
jij_cimod-1.7.3.dist-info/RECORD
jij_cimod-1.7.3.dist-info/licenses/LICENSE
