Metadata-Version: 2.1
Name: jij-cimod
Version: 1.7.3
Summary: C++ library for a binary (and polynomial) quadratic model.
Keywords: QUBO,Ising,optimization,binary quadratic model,BQM,dimod
Author-Email: "Jij Inc." <info@openjij.org>
License: Apache License 2.0
Classifier: Development Status :: 5 - Production/Stable
Classifier: License :: OSI Approved :: Apache Software License
Classifier: Intended Audience :: Science/Research
Classifier: Intended Audience :: Developers
Classifier: Programming Language :: Python
Classifier: Programming Language :: Python :: 3.9
Classifier: Programming Language :: Python :: 3.10
Classifier: Programming Language :: Python :: 3.11
Classifier: Programming Language :: Python :: 3.12
Classifier: Programming Language :: Python :: 3.13
Classifier: Programming Language :: Python :: 3 :: Only
Classifier: Programming Language :: Python :: Implementation :: CPython
Classifier: Programming Language :: C++
Classifier: Operating System :: Microsoft :: Windows
Classifier: Operating System :: POSIX
Classifier: Operating System :: MacOS
Classifier: Topic :: Scientific/Engineering
Classifier: Topic :: Scientific/Engineering :: Mathematics
Classifier: Topic :: Scientific/Engineering :: Physics
Classifier: Topic :: Software Development :: Libraries :: Python Modules
Project-URL: Homepage, https://www.openjij.org
Project-URL: Source, https://github.com/Jij-Inc/cimod
Project-URL: Documentation, https://jij-inc.github.io/Cimod-Documentation/
Project-URL: Python Documentation, https://jij-inc.github.io/cimod/
Requires-Python: <3.14,>=3.9
Requires-Dist: numpy<2.4,>=1.19.3
Requires-Dist: scipy<1.16,>=1.5.4
Requires-Dist: dimod<0.13,>=0.9.11
